{"cameraMode":{"drawMode":0,"name":"Shaded","section":"Shading Mode"},"sceneLighting":true,"audioPlay":false,"sceneViewState":{"showFog":true,"showMaterialUpdate":false,"showSkybox":true,"showFlares":true,"showImageEffects":true,"showParticleSystems":true},"in2DMode":false,"pivot":{"x":3.1190922260284426,"y":1.2433912754058838,"z":-0.3494725227355957},"rotation":{"x":0.129914790391922,"y":0.49170416593551638,"z":-0.07446923851966858,"w":0.8577936291694641},"size":4.157656192779541,"orthographic":false}